ScaledgeWhisper/__init__.py
ScaledgeWhisper/audio.py
ScaledgeWhisper/cli.py
ScaledgeWhisper/feature_extractor.py
ScaledgeWhisper/live_transcribe.py
ScaledgeWhisper/py.typed
ScaledgeWhisper/tokenizer.py
ScaledgeWhisper/transcribe.py
ScaledgeWhisper/utils.py
ScaledgeWhisper/vad.py
ScaledgeWhisper/version.py
ScaledgeWhisper/assets/__init__.py
ScaledgeWhisper/assets/py.typed
ScaledgeWhisper/assets/silero_decoder_v5.onnx
ScaledgeWhisper/assets/silero_encoder_v5.onnx
ScaledgeWhisper/test/__init__.py
ScaledgeWhisper/test/conftest.py
ScaledgeWhisper/test/test_tokenizer.py
ScaledgeWhisper/test/test_transcribe.py
ScaledgeWhisper/test/test_utils.py
ScaledgeWhisper/test/data/__init__.py
ScaledgeWhisper/test/data/hotwords.mp3
ScaledgeWhisper/test/data/jfk.flac
ScaledgeWhisper/test/data/multilingual.mp3
ScaledgeWhisper/test/data/physicsworks.wav
ScaledgeWhisper/test/data/stereo_diarization.wav
scaledgewhisper-1.1.4.dist-info/licenses/LICENSE
scaledgewhisper-1.1.4.dist-info/METADATA
scaledgewhisper-1.1.4.dist-info/WHEEL
scaledgewhisper-1.1.4.dist-info/entry_points.txt
scaledgewhisper-1.1.4.dist-info/top_level.txt
scaledgewhisper-1.1.4.dist-info/RECORD
