Metadata-Version: 2.4
Name: ScaledgeWhisper
Version: 1.1.4
Summary: Faster Whisper transcription with CTranslate2 with Live Capabilities for Edge Devices
Author: ScaledgeTechnology
Author-email: Scaledge.ml@gmail.com
License: MIT
Keywords: openai whisper faster-whisper speech ctranslate2 inference quantization transformer
Classifier: Development Status :: 4 - Beta
Classifier: Intended Audience :: Developers
Classifier: Intended Audience :: Science/Research
Classifier: License :: OSI Approved :: MIT License
Classifier: Programming Language :: Python :: 3
Classifier: Programming Language :: Python :: 3 :: Only
Classifier: Programming Language :: Python :: 3.9
Classifier: Programming Language :: Python :: 3.10
Classifier: Programming Language :: Python :: 3.11
Classifier: Topic :: Scientific/Engineering :: Artificial Intelligence
Requires-Python: >=3.9
License-File: LICENSE
Requires-Dist: av>=14.0.1
Requires-Dist: ctranslate2>=4.5.0
Requires-Dist: GPUtil>=1.4.0
Requires-Dist: huggingface_hub>=0.27.0
Requires-Dist: keyboard>=0.13.5
Requires-Dist: numpy>=2.2.0
Requires-Dist: onnxruntime>=1.20.1
Requires-Dist: psutil>=6.0.0
Requires-Dist: pyaudio>=0.2.14
Requires-Dist: pytest>=8.3.4
Requires-Dist: Requests>=2.32.3
Requires-Dist: setuptools>=75.8.0
Requires-Dist: tokenizers>=0.21.0
Requires-Dist: torch>=2.5.1
Requires-Dist: tqdm>=4.67.1
Provides-Extra: conversion
Requires-Dist: transformers[torch]>=4.23; extra == "conversion"
Provides-Extra: dev
Requires-Dist: black==23.*; extra == "dev"
Requires-Dist: flake8==6.*; extra == "dev"
Requires-Dist: isort==5.*; extra == "dev"
Requires-Dist: pytest==7.*; extra == "dev"
Dynamic: author
Dynamic: author-email
Dynamic: classifier
Dynamic: description
Dynamic: description-content-type
Dynamic: keywords
Dynamic: license
Dynamic: license-file
Dynamic: provides-extra
Dynamic: requires-dist
Dynamic: requires-python
Dynamic: summary
